fastatoms/__init__.py
fastatoms/_version.py
fastatoms-0.0.2.dist-info/METADATA
fastatoms-0.0.2.dist-info/WHEEL
fastatoms-0.0.2.dist-info/licenses/LICENSE
fastatoms-0.0.2.dist-info/RECORD
